st_pptx_viewer/__init__.py
st_pptx_viewer/app.py
st_pptx_viewer/viewer.py
st_pptx_viewer-1.2.1.dist-info/licenses/LICENSE
st_pptx_viewer-1.2.1.dist-info/METADATA
st_pptx_viewer-1.2.1.dist-info/WHEEL
st_pptx_viewer-1.2.1.dist-info/top_level.txt
st_pptx_viewer-1.2.1.dist-info/RECORD
