Metadata-Version: 2.4
Name: st-pptx-viewer
Version: 1.2.1
Summary: A Streamlit component for rendering PowerPoint presentations using PptxViewJS
Author: PptxViewJS Contributors
License-Expression: MIT
Project-URL: Homepage, https://gptsci.com/pptxviewjs/
Project-URL: Documentation, https://github.com/gptsci/st_pptx_viewer/blob/main/st_pptx_viewer/README.md
Project-URL: Repository, https://github.com/gptsci/st_pptx_viewer
Project-URL: Bug Reports, https://github.com/gptsci/st_pptx_viewer/issues
Keywords: streamlit,pptx,powerpoint,viewer,presentation,component
Classifier: Development Status :: 4 - Beta
Classifier: Intended Audience :: Developers
Classifier: Topic :: Software Development :: Libraries :: Python Modules
Classifier: Programming Language :: Python :: 3
Classifier: Programming Language :: Python :: 3.8
Classifier: Programming Language :: Python :: 3.9
Classifier: Programming Language :: Python :: 3.10
Classifier: Programming Language :: Python :: 3.11
Classifier: Programming Language :: Python :: 3.12
Requires-Python: >=3.8
License-File: LICENSE
Requires-Dist: streamlit>=1.0.0
Dynamic: license-file
